json2dir/__init__.py
json2dir/cli.py
json2dir/core.py
json2dir-0.1.0.dist-info/METADATA
json2dir-0.1.0.dist-info/WHEEL
json2dir-0.1.0.dist-info/entry_points.txt
json2dir-0.1.0.dist-info/licenses/LICENSE
json2dir-0.1.0.dist-info/RECORD
