Metadata-Version: 2.3
Name: json2dir
Version: 0.1.0
Summary: Convert JSON to directory structure and vice versa
Project-URL: Homepage, https://github.com/themrsami/json2dir
Project-URL: Bug Tracker, https://github.com/themrsami/json2dir/issues
Author-email: Usama <usamanazir13@gmail.com>
Classifier: License :: OSI Approved :: MIT License
Classifier: Operating System :: OS Independent
Classifier: Programming Language :: Python :: 3
Requires-Python: >=3.7
